cartonnage.py
cartonnage-0.1.4.dist-info/licenses/LICENSE
cartonnage-0.1.4.dist-info/METADATA
cartonnage-0.1.4.dist-info/WHEEL
cartonnage-0.1.4.dist-info/top_level.txt
cartonnage-0.1.4.dist-info/RECORD
